doppler/__init__.py
doppler/cannon.py
doppler/lsf.py
doppler/payne.py
doppler/reader.py
doppler/rv.py
doppler/spec1d.py
doppler/utils.py
doppler/data/apVisit-r13-5095-55844-128.fits
doppler/data/apVisit-r13-9518-57729-104.fits
doppler/data/cannongrid_3000_18000_coolstars_norm_cubic_model.pkl
doppler/data/cannongrid_3000_18000_hotdwarfs_norm_cubic_model.pkl
doppler/data/spec-3586-55181-0500.fits
thedoppler-1.1.30.data/scripts/doppler
thedoppler-1.1.30.dist-info/licenses/LICENSE
thedoppler-1.1.30.dist-info/METADATA
thedoppler-1.1.30.dist-info/WHEEL
thedoppler-1.1.30.dist-info/top_level.txt
thedoppler-1.1.30.dist-info/RECORD
