Metadata-Version: 2.4
Name: thedoppler
Version: 1.1.30
Summary: Generic Radial Velocity Software
Home-page: https://github.com/dnidever/doppler
Author: David Nidever
Author-email: David Nidever <dnidever@montana.edu>
Maintainer-email: David Nidever <dnidever@montana.edu>
License: MIT License
Project-URL: Documentation, https://doppler.readthedocs.org
Project-URL: Repository, https://github.com/dnidever/doppler
Keywords: spectra,radial velocity,stars
Classifier: Development Status :: 3 - Alpha
Classifier: License :: OSI Approved :: MIT License
Classifier: Programming Language :: Python
Requires-Python: >=3.9
License-File: LICENSE
Requires-Dist: scipy
Requires-Dist: numpy
Requires-Dist: matplotlib
Requires-Dist: astropy
Requires-Dist: dill
Requires-Dist: dlnpyutils
Requires-Dist: emcee
Requires-Dist: corner
Requires-Dist: annieslasso
Requires-Dist: gdown
Provides-Extra: gui
Requires-Dist: PyQt5; extra == "gui"
Provides-Extra: cli
Requires-Dist: rich; extra == "cli"
Requires-Dist: click; extra == "cli"
Dynamic: author
Dynamic: home-page
Dynamic: license-file
